amberdata/__init__.py
amberdata/client.py
amberdata/queries.py
amberdata/types.py
amberdata-0.1.1.dist-info/WHEEL
amberdata-0.1.1.dist-info/METADATA
amberdata-0.1.1.dist-info/RECORD
